llama_index/llms/cerebras/__init__.py
llama_index/llms/cerebras/base.py
llama_index_llms_cerebras-0.3.1.dist-info/METADATA
llama_index_llms_cerebras-0.3.1.dist-info/WHEEL
llama_index_llms_cerebras-0.3.1.dist-info/licenses/LICENSE
llama_index_llms_cerebras-0.3.1.dist-info/RECORD
