Metadata-Version: 2.4
Name: llama-index-llms-cerebras
Version: 0.3.1
Summary: llama-index llms cerebras integration
Author-email: Cerebras <support@cerebras.ai>
License-Expression: MIT
License-File: LICENSE
Requires-Python: <4.0,>=3.9
Requires-Dist: llama-index-core<0.15,>=0.13.0
Requires-Dist: llama-index-llms-openai-like<0.6,>=0.5.0
